monglo/__init__.py
monglo/adapters/__init__.py
monglo/adapters/base.py
monglo/adapters/django.py
monglo/adapters/fastapi.py
monglo/adapters/flask.py
monglo/adapters/starlette.py
monglo/auth/__init__.py
monglo/auth/authentication_backend.py
monglo/auth/base.py
monglo/auth/mongodb_backend.py
monglo/auth/session.py
monglo/auth/simple.py
monglo/core/__init__.py
monglo/core/config.py
monglo/core/engine.py
monglo/core/introspection.py
monglo/core/model_admin.py
monglo/core/query_builder.py
monglo/core/registry.py
monglo/core/relationships.py
monglo/fields/__init__.py
monglo/fields/base.py
monglo/fields/custom.py
monglo/fields/embedded.py
monglo/fields/files.py
monglo/fields/primitives.py
monglo/fields/references.py
monglo/operations/__init__.py
monglo/operations/aggregations.py
monglo/operations/audit.py
monglo/operations/crud.py
monglo/operations/export.py
monglo/operations/pagination.py
monglo/operations/search.py
monglo/operations/transactions.py
monglo/operations/validation.py
monglo/serializers/__init__.py
monglo/serializers/document.py
monglo/serializers/json.py
monglo/serializers/table.py
monglo/ui_helpers/__init__.py
monglo/ui_helpers/django.py
monglo/ui_helpers/fastapi.py
monglo/ui_helpers/flask.py
monglo/utils/__init__.py
monglo/utils/formatters.py
monglo/utils/index_analyzer.py
monglo/utils/validators.py
monglo/views/__init__.py
monglo/views/base.py
monglo/views/document_view.py
monglo/views/relationship_view.py
monglo/views/table_view.py
monglo/widgets/__init__.py
monglo/widgets/base.py
monglo/widgets/custom.py
monglo/widgets/displays.py
monglo/widgets/inputs.py
monglo/widgets/selects.py
monglo_ui/README.md
monglo_ui/__init__.py
monglo_ui/static/css/admin.css
monglo_ui/static/js/create-modal.js
monglo_ui/static/js/dark-mode.js
monglo_ui/static/js/document-view.js
monglo_ui/static/js/edit-modal.js
monglo_ui/static/js/modals.js
monglo_ui/static/js/relationship-graph.js
monglo_ui/static/js/sidebar-resize.js
monglo_ui/static/js/table-view.js
monglo-0.1.1.dist-info/METADATA
monglo-0.1.1.dist-info/WHEEL
monglo-0.1.1.dist-info/licenses/LICENSE
monglo-0.1.1.dist-info/RECORD
