Metadata-Version: 2.4
Name: Monglo
Version: 0.1.1
Summary: A framework-agnostic MongoDB admin library with intelligent relationship detection and dual views
Project-URL: Homepage, https://github.com/me-umar/monglo
Project-URL: Repository, https://github.com/me-umar/monglo
Project-URL: Issues, https://github.com/me-umar/monglo/issues
Project-URL: Changelog, https://github.com/me-umar/monglo/blob/main/CHANGELOG.md
Author-email: Mehar Umar <contact@meharumar.codes>
Maintainer-email: Mehar Umar <contact@meharumar.codes>
License: MIT
License-File: LICENSE
Keywords: admin,async,crud,database,django,fastapi,flask,introspection,mongoadmin,mongodb,motor,relationships,schema
Classifier: Development Status :: 3 - Alpha
Classifier: Framework :: Django
Classifier: Framework :: FastAPI
Classifier: Framework :: Flask
Classifier: Intended Audience :: Developers
Classifier: License :: OSI Approved :: MIT License
Classifier: Operating System :: OS Independent
Classifier: Programming Language :: Python :: 3
Classifier: Programming Language :: Python :: 3.10
Classifier: Programming Language :: Python :: 3.11
Classifier: Programming Language :: Python :: 3.12
Classifier: Topic :: Database
Classifier: Topic :: Internet :: WWW/HTTP :: Dynamic Content
Classifier: Topic :: Software Development :: Libraries :: Python Modules
Classifier: Typing :: Typed
Requires-Python: >=3.10
Requires-Dist: motor>=3.3.0
Requires-Dist: pydantic-settings>=2.0.0
Requires-Dist: pydantic>=2.0.0
Requires-Dist: pymongo>=4.5.0
Requires-Dist: typing-extensions>=4.8.0
Provides-Extra: all
Requires-Dist: django>=4.2.0; extra == 'all'
Requires-Dist: fastapi>=0.104.0; extra == 'all'
Requires-Dist: flask-cors>=4.0.0; extra == 'all'
Requires-Dist: flask>=3.0.0; extra == 'all'
Requires-Dist: starlette>=0.32.0; extra == 'all'
Requires-Dist: uvicorn[standard]>=0.24.0; extra == 'all'
Provides-Extra: dev
Requires-Dist: black>=23.11.0; extra == 'dev'
Requires-Dist: build>=1.0.0; extra == 'dev'
Requires-Dist: mypy>=1.7.0; extra == 'dev'
Requires-Dist: pytest-asyncio>=0.21.0; extra == 'dev'
Requires-Dist: pytest-cov>=4.1.0; extra == 'dev'
Requires-Dist: pytest-mock>=3.12.0; extra == 'dev'
Requires-Dist: pytest>=7.4.0; extra == 'dev'
Requires-Dist: ruff>=0.1.0; extra == 'dev'
Requires-Dist: twine>=4.0.0; extra == 'dev'
Provides-Extra: django
Requires-Dist: django>=4.2.0; extra == 'django'
Provides-Extra: fastapi
Requires-Dist: fastapi>=0.104.0; extra == 'fastapi'
Requires-Dist: uvicorn[standard]>=0.24.0; extra == 'fastapi'
Provides-Extra: flask
Requires-Dist: flask-cors>=4.0.0; extra == 'flask'
Requires-Dist: flask>=3.0.0; extra == 'flask'
Provides-Extra: starlette
Requires-Dist: starlette>=0.32.0; extra == 'starlette'
